{"provider":{"name":"time"},"consumer":{"name":"greeting"},"interactions":[{"providerState":"time is set to 01-07-2016","description":"provide the time from greeting","request":{"method":"GET","path":"/time"},"response":{"status":200,"headers":{"Content-Type":"text/plain"},"body":"01-07-2016"}},{"providerState":"time is set to 01-07-2017","description":"provide the time from greeting","request":{"method":"GET","path":"/time"},"response":{"status":200,"headers":{"Content-Type":"text/plain"},"body":"01-07-2017"}}]}